discourse_sso_oidc_bridge/__init__.py
discourse_sso_oidc_bridge/app.py
discourse_sso_oidc_bridge/constants.py
discourse_sso_oidc_bridge/default_config.py
discourse_sso_oidc_bridge/templates/403.html
discourse_sso_oidc_bridge_consideratio-2.0.0.dist-info/AUTHORS
discourse_sso_oidc_bridge_consideratio-2.0.0.dist-info/LICENCE
discourse_sso_oidc_bridge_consideratio-2.0.0.dist-info/METADATA
discourse_sso_oidc_bridge_consideratio-2.0.0.dist-info/WHEEL
discourse_sso_oidc_bridge_consideratio-2.0.0.dist-info/top_level.txt
discourse_sso_oidc_bridge_consideratio-2.0.0.dist-info/RECORD
