Metadata-Version: 2.1
Name: discourse-sso-oidc-bridge-consideratio
Version: 2.0.0
Summary: A Flask app, wrapping a single OpenID Connect issuer with a Discourse SSO provider interface.
Home-page: https://github.com/consideratio/discourse-sso-oidc-bridge
Author: Erik Sundell
Author-email: erik+pypi@sundellopensource.se
License: Apache License 2.0
Keywords: discourse,oidc,sso
Platform: Linux
Platform: Mac OS X
Classifier: Programming Language :: Python :: 3
Classifier: License :: OSI Approved :: Apache Software License
Classifier: Operating System :: OS Independent
Requires-Python: >=3.6
License-File: LICENCE
License-File: AUTHORS
Requires-Dist: flask-pyoidc (==3.7.*)
Requires-Dist: flask (==2.0.*)
Requires-Dist: healthcheck
